README.txt
setup.py
cmdline_iaod/__init__.py
cmdline_iaod/__main__.py
cmdline_iaod/create_db.py
cmdline_iaod/intronIC_devlin.py
cmdline_iaod/reformatting.py
cmdline_iaod.egg-info/PKG-INFO
cmdline_iaod.egg-info/SOURCES.txt
cmdline_iaod.egg-info/dependency_links.txt
cmdline_iaod.egg-info/requires.txt
cmdline_iaod.egg-info/top_level.txt
scripts/search_functions.py