Metadata-Version: 1.0
Name: cmdline-iaod
Version: 0.1.0
Summary: Makes database of intron annotation information
Home-page: UNKNOWN
Author: Devlin Moyer
Author-email: devmoy@gmail.com
License: MIT
Keywords: U12-dependent introns,genomics,RNA-splicing
Platform: UNKNOWN
